traggle/__init__.py
traggle/notes.py
traggle/translator.py
traggle-0.0.2.dist-info/METADATA
traggle-0.0.2.dist-info/WHEEL
traggle-0.0.2.dist-info/top_level.txt
traggle-0.0.2.dist-info/RECORD
