Metadata-Version: 2.1
Name: traggle
Version: 0.0.2
Summary: Library that simplifies working with the "Traggle" site API
Home-page: https://github.com/Trejgus/
Author: duckduck
Author-email: dimondtp@gmail.com
Project-URL: GitHub, https://github.com/Trejgus/
Keywords: files speedfiles
Classifier: Programming Language :: Python :: 3.9
Classifier: License :: OSI Approved :: MIT License
Classifier: Operating System :: OS Independent
Requires-Python: >=3.6
Requires-Dist: requests >=2.31.0
